maritest/__init__.py
maritest/assertion.py
maritest/client.py
maritest/custom_auth.py
maritest/response.py
maritest/serializable.py
maritest/version.py
maritest/utils/__init__.py
maritest/utils/deprecation.py
maritest/utils/dict_lookups.py
maritest/utils/exceptions.py
maritest/utils/factory.py
tests/__init__.py
tests/test_assertion.py
tests/test_clients.py
tests/test_custom_auth.py
tests/test_deprecation.py
tests/test_dict_lookups.py
tests/test_factory_logger.py
tests/test_json_serializer.py
tests/test_response.py
maritest-0.6.0.dist-info/LICENSE
maritest-0.6.0.dist-info/METADATA
maritest-0.6.0.dist-info/WHEEL
maritest-0.6.0.dist-info/top_level.txt
maritest-0.6.0.dist-info/RECORD
