Metadata-Version: 2.1
Name: maritest
Version: 0.6.0
Summary: API testing framework for simplify assertion
Home-page: https://github.com/sodrooome/maritest
Author: Ryan Febriansyah
Author-email: ryanfebriansyah72@gmail.com
License: UNKNOWN
Platform: UNKNOWN
Classifier: Development Status :: 4 - Beta
Classifier: Operating System :: OS Independent
Classifier: Intended Audience :: Developers
Classifier: Natural Language :: English
Classifier: Programming Language :: Python :: 3.7
Classifier: Programming Language :: Python :: 3.8
Classifier: Programming Language :: Python :: 3.9
Requires-Python: >=3.7
License-File: LICENSE
Requires-Dist: requests
